[
    {
        "id": 9226,
        "lemma_1": "alābha 2"
    },
    {
        "id": 63510,
        "lemma_1": "sukhallikānuyoga"
    },
    {
        "id": 82839,
        "lemma_1": "anusarati 2.1"
    },
    {
        "id": 82836,
        "lemma_1": "ditta 2.1"
    },
    {
        "id": 82834,
        "lemma_1": "ākoṭesi 2"
    },
    {
        "id": 82831,
        "lemma_1": "āluppa"
    },
    {
        "id": 82969,
        "lemma_1": "kāya 1.9"
    },
    {
        "id": 82829,
        "lemma_1": "duppavesa"
    },
    {
        "id": 21111,
        "lemma_1": "kāmūpapatti"
    },
    {
        "id": 20478,
        "lemma_1": "karatiya 1"
    },
    {
        "id": 32553,
        "lemma_1": "diṭṭhivipatti"
    },
    {
        "id": 44574,
        "lemma_1": "pasaṅga 1"
    },
    {
        "id": 64171,
        "lemma_1": "supparodha"
    },
    {
        "id": 82968,
        "lemma_1": "sumukha 2"
    },
    {
        "id": 82967,
        "lemma_1": "pajjunna 2"
    },
    {
        "id": 82966,
        "lemma_1": "pañcālacaṇḍa 2"
    },
    {
        "id": 39926,
        "lemma_1": "pañcālacaṇḍa"
    },
    {
        "id": 51379,
        "lemma_1": "mandiya 2"
    },
    {
        "id": 82965,
        "lemma_1": "hiri 2"
    },
    {
        "id": 25341,
        "lemma_1": "gopāla 2"
    }
]